immutable/__init__.py
immutable/checktype.py
immutable/decorator.py
immutable/deep.py
immutable/exceptions.py
immutable/extraproxies.py
immutable/immutable.py
immutable/proxy.py
immutable/register.py
immutable/superpatch.py
immutable_proxy-0.1.1.dist-info/LICENSE
immutable_proxy-0.1.1.dist-info/METADATA
immutable_proxy-0.1.1.dist-info/WHEEL
immutable_proxy-0.1.1.dist-info/top_level.txt
immutable_proxy-0.1.1.dist-info/RECORD
