Metadata-Version: 2.1
Name: immutable-proxy
Version: 0.1.1
Summary: Provides a proxy to an object that prevents mutation at any depth
Author-email: José Carlos Díaz-Ramos <carlitos.diaz.ramos@gmail.com>
License: The MIT License (MIT)
Project-URL: Homepage, https://github.com/carlitos-diaz-ramos/immutable
Keywords: immutable object,proxy
Classifier: License :: OSI Approved :: MIT License
Classifier: Programming Language :: Python
Classifier: Programming Language :: Python :: 3
Classifier: Topic :: Utilities
Requires-Python: >=3.9
License-File: LICENSE
Provides-Extra: dev
Requires-Dist: pytest ; extra == 'dev'
